{"sqlparse.utils": ["contextlib", "contextlib.contextmanager", "re", "re.compile", "collections"], "re": ["<builtin>.type", "enum", "functools._lru_cache_wrapper.wrapper", "copyreg", "functools.lru_cache", "functools.lru_cache.decorating_function", "sre_compile.compile", "<builtin>.globals", "<builtin>.chr", "re.Scanner", "sre_compile", "re.RegexFlag", "copyreg.pickle", "functools", "sre_parse"], "enum": ["enum.EnumMeta", "enum.IntFlag", "enum._EnumDict", "enum.Flag", "enum.IntEnum", "<builtin>.object", "enum.Enum", "types", "enum.auto"], "types": ["<builtin>.type", "types._c", "types._C", "types._g", "types.DynamicClassAttribute", "types._GeneratorWrapper", "<builtin>.globals", "types._ag", "types._cell_factory", "<builtin>.object"], "<builtin>.type": [], "types._cell_factory": [], "types._g": [], "types._c": [], "types._ag": [], "types._C": [], "<builtin>.object": [], "types.DynamicClassAttribute": [], "types._GeneratorWrapper": ["<builtin>.property"], "<builtin>.property": [], "<builtin>.globals": [], "enum.auto": [], "enum._EnumDict": [], "enum.EnumMeta": ["<builtin>.staticmethod", "<builtin>.classmethod", "<builtin>.property"], "<builtin>.classmethod": [], "<builtin>.staticmethod": [], "enum.Enum": ["<builtin>.classmethod", "types.DynamicClassAttribute.__init__"], "types.DynamicClassAttribute.__init__": ["<builtin>.getattr", "<builtin>.bool"], "<builtin>.getattr": [], "<builtin>.bool": [], "enum.IntEnum": [], "enum.Flag": ["<builtin>.classmethod"], "enum.IntFlag": ["<builtin>.classmethod"], "sre_compile": ["sre_constants", "<builtin>.tuple", "sre_parse"], "sre_parse": ["sre_constants", "sre_parse.Verbose", "sre_parse.SubPattern", "sre_parse.State", "<builtin>.frozenset", "sre_parse.Tokenizer"], "sre_constants": ["sre_constants.error", "sre_constants._NamedIntConstant", "sre_constants._makecodes"], "sre_constants.error": [], "sre_constants._NamedIntConstant": [], "sre_constants._makecodes": ["<builtin>.enumerate", "<str>.split", "<str>.strip", "<builtin>.globals"], "<str>.strip": [], "<str>.split": [], "<builtin>.enumerate": [], "<builtin>.frozenset": [], "sre_parse.Verbose": [], "sre_parse.State": ["<builtin>.property"], "sre_parse.SubPattern": [], "sre_parse.Tokenizer": ["<builtin>.property"], "<builtin>.tuple": [], "functools": ["abc", "functools.cached_property", "functools.partial", "functools.partialmethod", "functools._HashedSeq", "reprlib", "functools.singledispatchmethod", "collections.namedtuple", "<builtin>.object", "collections"], "abc": ["abc.abstractclassmethod", "_py_abc", "abc.abstractstaticmethod", "abc.abstractproperty", "abc.ABC"], "abc.abstractclassmethod": [], "abc.abstractstaticmethod": [], "abc.abstractproperty": [], "_py_abc": ["_py_abc.ABCMeta", "_weakrefset"], "_weakrefset": ["_weakrefset.WeakSet", "_weakrefset._IterationGuard"], "_weakrefset._IterationGuard": [], "_weakrefset.WeakSet": [], "_py_abc.ABCMeta": [], "abc.ABC": [], "collections": ["collections.Counter", "collections._OrderedDictItemsView", "collections._OrderedDictKeysView", "collections._OrderedDictValuesView", "collections.ChainMap", "collections.UserString", "collections.OrderedDict", "keyword", "collections.UserDict", "reprlib", "operator", "collections._Link", "heapq", "collections.UserList"], "operator": ["operator.attrgetter", "operator.itemgetter", "operator.methodcaller"], "operator.attrgetter": [], "operator.itemgetter": [], "operator.methodcaller": [], "keyword": ["<builtin>.frozenset"], "heapq": ["_heapq"], "_heapq": [], "reprlib": ["reprlib.Repr.__init__", "reprlib.Repr"], "reprlib.Repr": [], "reprlib.Repr.__init__": [], "collections._OrderedDictKeysView": [], "collections._OrderedDictItemsView": [], "collections._OrderedDictValuesView": [], "collections._Link": [], "collections.OrderedDict": ["<builtin>.object", "reprlib.recursive_repr.decorating_function", "reprlib.recursive_repr", "<builtin>.classmethod"], "reprlib.recursive_repr": [], "reprlib.recursive_repr.decorating_function": ["<builtin>.getattr", "<builtin>.set"], "<builtin>.set": [], "collections.Counter": ["<builtin>.classmethod"], "collections.ChainMap": ["reprlib.recursive_repr.decorating_function", "reprlib.recursive_repr", "<builtin>.property", "<builtin>.classmethod"], "collections.UserDict": ["<builtin>.classmethod"], "collections.UserList": [], "collections.UserString": [], "functools.partial": ["reprlib.recursive_repr.decorating_function", "reprlib.recursive_repr"], "functools.partialmethod": ["<builtin>.property"], "collections.namedtuple": ["<str>.replace", "_collections._tuplegetter", "<builtin>.list", "<builtin>.ValueError", "<builtin>.len", "<builtin>.TypeError", "<builtin>.repr", "<builtin>.str", "<builtin>.set", "<builtin>.exec", "<builtin>.isinstance", "<builtin>.map", "<builtin>.classmethod", "<builtin>.tuple", "<builtin>.zip", "<builtin>.enumerate", "<builtin>.type", "<builtin>.dict", "<builtin>.reversed", "collections.<lambda1>", "<str>.join", "<str>.split"], "<builtin>.isinstance": [], "<builtin>.map": [], "<builtin>.list": [], "<builtin>.str": [], "<builtin>.TypeError": [], "<builtin>.ValueError": [], "<builtin>.len": [], "<builtin>.reversed": [], "<builtin>.zip": [], "<builtin>.dict": [], "<builtin>.repr": [], "<str>.join": [], "<builtin>.exec": [], "collections.<lambda1>": ["<builtin>.property", "operator.itemgetter.__init__"], "operator.itemgetter.__init__": [], "_collections._tuplegetter": [], "functools._HashedSeq": [], "functools.singledispatchmethod": ["<builtin>.property"], "functools.cached_property": [], "re.RegexFlag": [], "<builtin>.chr": [], "sre_compile.compile": ["sre_compile._code", "<map>.items", "sre_parse.parse", "sre_compile.dis", "<builtin>.print", "sre_compile.isstring", "<builtin>.tuple"], "sre_compile.isstring": ["<builtin>.isinstance"], "sre_parse.parse": ["sre_parse.Tokenizer.error", "sre_parse.Tokenizer.seek", "sre_parse.Tokenizer.__init__", "sre_parse.State.__init__", "sre_parse.fix_flags", "sre_parse._parse_sub", "sre_parse.SubPattern.dump"], "sre_parse.Tokenizer.__init__": ["<builtin>.isinstance", "<builtin>.str", "sre_parse.Tokenizer.__next"], "sre_parse.Tokenizer.__next": ["<builtin>.len", "sre_parse.Tokenizer.error"], "sre_parse.Tokenizer.error": ["sre_parse.Tokenizer.tell", "sre_parse.Tokenizer.error"], "sre_parse.Tokenizer.tell": ["<builtin>.len"], "sre_parse.State.__init__": [], "sre_parse._parse_sub": ["", "sre_parse.Tokenizer.tell", "sre_parse.Tokenizer.match", "append", "<builtin>.len", "sre_parse.SubPattern.append", "sre_parse.SubPattern.__init__", "extend"], "sre_parse.Tokenizer.match": ["sre_parse.Tokenizer.__next"], "sre_parse.SubPattern.__init__": [], "extend": [], "append": [], "sre_parse.SubPattern.append": ["append"], "sre_parse.Tokenizer.seek": ["sre_parse.Tokenizer.__next"], "sre_parse.fix_flags": ["<builtin>.isinstance", "<builtin>.ValueError"], "sre_parse.SubPattern.dump": ["<builtin>.isinstance", "<builtin>.str", "<builtin>.print", "<builtin>.enumerate"], "<builtin>.print": [], "sre_compile._code": ["sre_compile._compile", "append", "sre_compile._compile_info"], "sre_compile._compile_info": ["", "sre_compile._get_charset_prefix", "<builtin>.len", "sre_parse.SubPattern.getwidth", "sre_compile._optimize_charset", "sre_compile._compile_charset", "sre_compile._get_literal_prefix", "extend"], "sre_parse.SubPattern.getwidth": ["<builtin>.max", "<builtin>.min"], "<builtin>.min": [], "<builtin>.max": [], "sre_compile._get_literal_prefix": ["sre_compile._get_iscased", "", "<builtin>.len", "sre_compile._combine_flags", "sre_compile._get_literal_prefix", "extend"], "sre_compile._get_iscased": [], "sre_compile._combine_flags": [], "sre_compile._get_charset_prefix": ["sre_compile._get_iscased", "", "sre_compile._combine_flags", "<builtin>.map", "<builtin>.range", "<builtin>.any"], "<builtin>.range": [], "<builtin>.any": [], "sre_compile._optimize_charset": ["append", "<builtin>.len", "sre_compile._bytes_to_codes", "sre_compile._mk_bitmap", "<builtin>.bytes", "<builtin>.map", "<builtin>.range", "<builtin>.any", "<builtin>.bytearray"], "<builtin>.bytearray": [], "sre_compile._mk_bitmap": ["<builtin>.len", "<builtin>.range"], "<builtin>.bytes": [], "sre_compile._bytes_to_codes": ["<builtin>.len", "<builtin>.memoryview"], "<builtin>.memoryview": [], "sre_compile._compile_charset": ["", "extend", "sre_constants.error.__init__"], "sre_constants.error.__init__": ["<builtin>.isinstance", "<builtin>.super"], "<builtin>.super": [], "sre_compile._compile": ["", "sre_compile._compile_charset", "sre_compile._compile", "sre_compile._optimize_charset", "sre_compile._combine_flags", "sre_constants.error.__init__", "sre_compile._simple"], "sre_compile._simple": ["<builtin>.len", "sre_compile._simple"], "sre_compile.dis": ["sre_compile.dis.dis_", "<builtin>.str", "<builtin>.set", "<builtin>.len"], "sre_compile.dis.dis_": ["<builtin>.ValueError", "<builtin>.str", "sre_compile.dis.dis_.print_2", "sre_compile.dis.dis_", "<builtin>.map", "sre_compile._hex_code", "<builtin>.list", "sre_compile.dis.dis_.print_", "<builtin>.range", "<builtin>.bin", "<builtin>.chr"], "<builtin>.bin": [], "sre_compile.dis.dis_.print_": ["<builtin>.print"], "sre_compile.dis.dis_.print_2": ["<builtin>.print"], "sre_compile._hex_code": [], "<map>.items": [], "functools.lru_cache": ["<builtin>.isinstance", "functools.update_wrapper", "functools._lru_cache_wrapper", "<builtin>.TypeError", "<builtin>.callable"], "<builtin>.callable": [], "functools._lru_cache_wrapper": ["<builtin>.object", "_thread.RLock"], "_thread.RLock": [], "functools.update_wrapper": ["<builtin>.getattr"], "functools.lru_cache.decorating_function": ["functools._lru_cache_wrapper", "functools.update_wrapper"], "functools._lru_cache_wrapper.wrapper": ["re._compile_repl", "functools._make_key"], "functools._make_key": ["<builtin>.type", "<builtin>.len", "functools._HashedSeq.__init__", "<builtin>.tuple"], "functools._HashedSeq.__init__": ["<builtin>.hash"], "<builtin>.hash": [], "re._compile_repl": ["sre_parse.parse_template"], "sre_parse.parse_template": ["", "<builtin>.int", "sre_parse.Tokenizer.match", "append", "<builtin>.len", "sre_parse.Tokenizer.error", "sre_parse.Tokenizer.__init__", "sre_parse.parse_template.addgroup", "<builtin>.IndexError", "<str>.isidentifier", "sre_parse.Tokenizer.get", "<builtin>.isinstance", "sre_parse.Tokenizer.getuntil", "<builtin>.chr"], "sre_parse.Tokenizer.get": ["sre_parse.Tokenizer.__next"], "<builtin>.int": [], "sre_parse.parse_template.addgroup": ["append", "sre_parse.Tokenizer.error"], "sre_parse.Tokenizer.getuntil": ["<builtin>.len", "sre_parse.Tokenizer.error", "sre_parse.Tokenizer.__next"], "<str>.isidentifier": [], "<builtin>.IndexError": [], "copyreg": [], "copyreg.pickle": ["copyreg.constructor", "<builtin>.TypeError", "<builtin>.callable"], "copyreg.constructor": ["<builtin>.TypeError", "<builtin>.callable"], "re.Scanner": [], "contextlib": ["contextlib.AsyncExitStack", "contextlib._GeneratorContextManagerBase", "contextlib.AbstractContextManager", "contextlib.redirect_stdout", "contextlib._AsyncGeneratorContextManager", "contextlib.ContextDecorator", "contextlib._GeneratorContextManager", "contextlib.suppress", "types", "contextlib.nullcontext", "functools", "collections", "contextlib.ExitStack", "abc", "contextlib.redirect_stderr", "contextlib._BaseExitStack", "contextlib._RedirectStream", "contextlib.closing", "contextlib.AbstractAsyncContextManager"], "contextlib.AbstractContextManager": ["<builtin>.classmethod", "abc.abstractmethod"], "abc.abstractmethod": [], "contextlib.AbstractAsyncContextManager": ["<builtin>.classmethod", "abc.abstractmethod"], "contextlib.ContextDecorator": [], "contextlib._GeneratorContextManagerBase": [], "contextlib._GeneratorContextManager": [], "contextlib._AsyncGeneratorContextManager": [], "contextlib.closing": [], "contextlib._RedirectStream": [], "contextlib.redirect_stdout": [], "contextlib.redirect_stderr": [], "contextlib.suppress": [], "contextlib._BaseExitStack": ["<builtin>.staticmethod"], "contextlib.ExitStack": [], "contextlib.AsyncExitStack": ["<builtin>.staticmethod"], "contextlib.nullcontext": [], "re.compile": ["re._compile"], "re._compile": ["<builtin>.next", "<builtin>.ValueError", "<builtin>.type", "<builtin>.len", "sre_compile.compile", "<builtin>.iter", "<builtin>.isinstance", "sre_compile.isstring", "<builtin>.TypeError"], "<builtin>.iter": [], "<builtin>.next": [], "contextlib.contextmanager": ["functools.wraps"], "functools.wraps": [], "sqlparse.tokens": ["sqlparse.tokens._TokenType"], "sqlparse.tokens._TokenType": [], "sqlparse.sql": ["sqlparse.sql.Identifier", "sqlparse.sql.Comment", "sqlparse.sql.Function", "sqlparse.sql.Having", "sqlparse.sql.TypedLiteral", "sqlparse.sql.Token", "sqlparse.sql.Values", "sqlparse.tokens", "sqlparse.sql.For", "re", "sqlparse.sql.TokenList", "sqlparse.sql.SquareBrackets", "sqlparse.sql.Comparison", "sqlparse.sql.If", "sqlparse.sql.Begin", "sqlparse.sql.NameAliasMixin", "sqlparse.utils", "sqlparse.sql.Case", "sqlparse.sql.IdentifierList", "sqlparse.sql.Assignment", "sqlparse.sql.Command", "sqlparse.sql.Where", "sqlparse.sql.Operation", "sqlparse.sql.Parenthesis", "sqlparse.sql.Statement"], "sqlparse.sql.NameAliasMixin": [], "sqlparse.sql.Token": [], "sqlparse.sql.TokenList": ["<builtin>.property"], "sqlparse.sql.Statement": [], "sqlparse.sql.Identifier": [], "sqlparse.sql.IdentifierList": [], "sqlparse.sql.TypedLiteral": [], "sqlparse.sql.Parenthesis": ["<builtin>.property"], "sqlparse.sql.SquareBrackets": ["<builtin>.property"], "sqlparse.sql.Assignment": [], "sqlparse.sql.If": [], "sqlparse.sql.For": [], "sqlparse.sql.Comparison": ["<builtin>.property"], "sqlparse.sql.Comment": [], "sqlparse.sql.Where": [], "sqlparse.sql.Having": [], "sqlparse.sql.Case": [], "sqlparse.sql.Function": [], "sqlparse.sql.Begin": [], "sqlparse.sql.Operation": [], "sqlparse.sql.Values": [], "sqlparse.sql.Command": [], "sqlparse.keywords": ["re", "re.compile", "sqlparse.tokens"], "sqlparse.lexer": ["sqlparse.tokens", "sqlparse.keywords", "sqlparse.lexer.Lexer", "sqlparse.utils", "io"], "io": ["abc", "io.RawIOBase", "io.IOBase", "io.TextIOBase", "io.BufferedIOBase"], "io.IOBase": [], "io.RawIOBase": [], "io.BufferedIOBase": [], "io.TextIOBase": [], "sqlparse.lexer.Lexer": ["<builtin>.staticmethod"], "sqlparse.formatter": ["sqlparse.exceptions", "sqlparse.filters"], "sqlparse.filters": ["sqlparse.filters.aligned_indent", "sqlparse.filters.others", "sqlparse.filters.tokens", "sqlparse.filters.reindent", "sqlparse.filters.right_margin", "sqlparse.filters.output"], "sqlparse.filters.others": ["sqlparse.filters.others.SpacesAroundOperatorsFilter", "sqlparse.filters.others.StripWhitespaceFilter", "sqlparse.tokens", "re", "sqlparse.sql", "sqlparse.filters.others.SerializerUnicode", "sqlparse.utils", "sqlparse.filters.others.StripCommentsFilter"], "sqlparse.filters.others.StripCommentsFilter": ["<builtin>.staticmethod"], "sqlparse.filters.others.StripWhitespaceFilter": ["<builtin>.staticmethod"], "sqlparse.filters.others.SpacesAroundOperatorsFilter": ["<builtin>.staticmethod"], "sqlparse.filters.others.SerializerUnicode": ["<builtin>.staticmethod"], "sqlparse.filters.output": ["sqlparse.filters.output.OutputFilter", "sqlparse.tokens", "sqlparse.filters.output.OutputPHPFilter", "sqlparse.filters.output.OutputPythonFilter", "sqlparse.sql"], "sqlparse.filters.output.OutputFilter": [], "sqlparse.filters.output.OutputPythonFilter": [], "sqlparse.filters.output.OutputPHPFilter": [], "sqlparse.filters.tokens": ["sqlparse.tokens", "sqlparse.filters.tokens._CaseFilter", "sqlparse.filters.tokens.KeywordCaseFilter", "sqlparse.filters.tokens.IdentifierCaseFilter", "sqlparse.filters.tokens.TruncateStringFilter"], "sqlparse.filters.tokens._CaseFilter": [], "sqlparse.filters.tokens.KeywordCaseFilter": [], "sqlparse.filters.tokens.IdentifierCaseFilter": [], "sqlparse.filters.tokens.TruncateStringFilter": [], "sqlparse.filters.reindent": ["sqlparse.filters.reindent.ReindentFilter", "sqlparse.sql", "sqlparse.tokens", "sqlparse.utils"], "sqlparse.filters.reindent.ReindentFilter": ["<builtin>.property"], "sqlparse.filters.right_margin": ["sqlparse.sql", "re", "sqlparse.tokens", "sqlparse.filters.right_margin.RightMarginFilter"], "sqlparse.filters.right_margin.RightMarginFilter": [], "sqlparse.filters.aligned_indent": ["sqlparse.filters.aligned_indent.AlignedIndentFilter", "sqlparse.sql", "sqlparse.tokens", "sqlparse.utils"], "sqlparse.filters.aligned_indent.AlignedIndentFilter": [], "sqlparse.exceptions": ["sqlparse.exceptions.SQLParseError"], "sqlparse.exceptions.SQLParseError": [], "sqlparse.cli": ["argparse", "io", "sqlparse.exceptions", "sqlparse"], "argparse": ["argparse._ActionsContainer", "argparse.HelpFormatter", "argparse.RawDescriptionHelpFormatter", "argparse.ArgumentError", "argparse.RawTextHelpFormatter", "argparse._StoreFalseAction", "argparse.FileType", "argparse._MutuallyExclusiveGroup", "re", "argparse.Action", "argparse.MetavarTypeHelpFormatter", "argparse._StoreConstAction", "argparse._SubParsersAction", "shutil", "argparse._AppendConstAction", "argparse._StoreAction", "argparse._ExtendAction", "os", "argparse._AttributeHolder", "argparse.Namespace", "gettext", "argparse._StoreTrueAction", "argparse._HelpAction", "argparse.ArgumentParser", "argparse._CountAction", "argparse._VersionAction", "argparse.ArgumentDefaultsHelpFormatter", "argparse._AppendAction", "argparse._ArgumentGroup", "argparse.ArgumentTypeError"], "os": ["abc", "append", "os._exists", "ntpath", "os._wrap_close", "<builtin>.set", "os._Environ", "os._fscodec", "<builtin>.globals", "posixpath", "os._Environ.__init__", "stat", "<builtin>.ImportError", "os.PathLike", "os._AddedDllDirectory", "extend", "os._createenviron", "os._add"], "stat": [], "<builtin>.ImportError": [], "ntpath": ["<builtin>.hasattr", "os", "stat", "genericpath"], "genericpath": ["os", "stat"], "<builtin>.hasattr": [], "posixpath": ["os", "stat", "genericpath"], "os._exists": ["<builtin>.globals"], "os._add": [], "os._Environ": [], "os._createenviron": ["os._createenviron.encodekey", "os._Environ.__init__"], "os._createenviron.encodekey": ["os._createenviron.encode"], "os._createenviron.encode": ["<builtin>.isinstance", "<builtin>.type", "<builtin>.TypeError"], "os._Environ.__init__": [], "os._fscodec": [], "os._wrap_close": [], "os.PathLike": ["<builtin>.classmethod", "abc.abstractmethod"], "os._AddedDllDirectory": [], "shutil": ["shutil.SameFileError", "lzma", "shutil.RegistryError", "append", "shutil.SpecialFileError", "bz2", "shutil.Error", "grp", "shutil.ReadError", "fnmatch", "zlib", "stat", "shutil._GiveupOnFastCopy", "collections.namedtuple", "shutil.ExecError", "os", "<builtin>.hasattr", "collections"], "fnmatch": ["functools._lru_cache_wrapper.wrapper", "functools.lru_cache", "functools.lru_cache.decorating_function", "re", "posixpath", "os", "functools"], "zlib": [], "bz2": ["_compression", "os", "threading", "_bz2", "<builtin>.object", "io", "warnings", "bz2.BZ2File"], "warnings": ["warnings.catch_warnings", "warnings._processoptions", "warnings.simplefilter", "warnings.WarningMessage", "warnings._OptionError", "warnings.filterwarnings", "<builtin>.hasattr"], "warnings._OptionError": [], "warnings.WarningMessage": [], "warnings.catch_warnings": [], "warnings._processoptions": ["warnings._setoption", "<builtin>.print"], "warnings._setoption": ["<builtin>.int", "re.escape", "<builtin>.len", "re", "warnings._getcategory", "warnings._getaction", "warnings.filterwarnings"], "warnings._getaction": [], "warnings._getcategory": ["<builtin>.issubclass", "<builtin>.getattr", "<builtin>.__import__"], "<builtin>.__import__": [], "<builtin>.issubclass": [], "re.escape": ["<builtin>.isinstance", "<builtin>.str"], "warnings.filterwarnings": ["re", "warnings._add_filter", "<builtin>.issubclass", "<builtin>.isinstance", "re.compile"], "warnings._add_filter": ["warnings._filters_mutated", "remove", "append", "insert"], "remove": [], "insert": [], "warnings._filters_mutated": [], "warnings.simplefilter": ["<builtin>.isinstance", "warnings._add_filter"], "_compression": ["io", "_compression.BaseStream", "_compression.DecompressReader"], "_compression.BaseStream": [], "_compression.DecompressReader": [], "threading": ["append", "threading.Condition", "collections.namedtuple", "threading.Thread", "threading._DummyThread", "threading.BoundedSemaphore", "traceback", "threading.Timer", "threading._MainThread.__init__", "_weakrefset", "collections", "<builtin>.hasattr", "threading.BrokenBarrierError", "threading._MainThread", "<builtin>.set", "itertools.count", "os", "_weakrefset.WeakSet.__init__", "threading.Event", "threading.Barrier", "threading.Semaphore", "_threading_local", "threading._RLock"], "threading._RLock": [], "threading.Condition": [], "threading.Semaphore": [], "threading.BoundedSemaphore": [], "threading.Event": [], "threading.Barrier": ["<builtin>.property"], "threading.BrokenBarrierError": [], "itertools.count": [], "_weakrefset.WeakSet.__init__": ["_weakref.ref", "<builtin>.set", "_weakrefset.WeakSet.update"], "_weakref.ref": [], "_weakrefset.WeakSet.update": ["_weakrefset.WeakSet.add", "_weakrefset.WeakSet._commit_removals"], "_weakrefset.WeakSet._commit_removals": [], "_weakrefset.WeakSet.add": ["_weakref.ref", "_weakrefset.WeakSet._commit_removals"], "threading.Thread": ["<builtin>.property"], "traceback": ["linecache", "traceback.FrameSummary", "traceback.StackSummary", "traceback.TracebackException", "collections"], "linecache": ["os", "tokenize", "functools"], "tokenize": ["codecs", "tokenize.group", "tokenize.TokenInfo", "re", "tokenize.maybe", "<builtin>.set", "tokenize.StopTokenizing", "tokenize._all_string_prefixes", "tokenize.TokenError", "<builtin>.sorted", "<builtin>.map", "tokenize.Untokenizer", "re.compile", "collections.namedtuple", "io", "<builtin>.any", "token", "collections"], "codecs": ["codecs.BufferedIncrementalDecoder", "<builtin>.SystemError", "codecs.Codec", "codecs.BufferedIncrementalEncoder", "codecs.StreamRecoder", "codecs.StreamReader", "encodings", "codecs.StreamReaderWriter", "codecs.CodecInfo", "codecs.IncrementalEncoder", "codecs.IncrementalDecoder", "codecs.StreamWriter"], "<builtin>.SystemError": [], "codecs.CodecInfo": [], "codecs.Codec": [], "codecs.IncrementalEncoder": [], "codecs.BufferedIncrementalEncoder": [], "codecs.IncrementalDecoder": [], "codecs.BufferedIncrementalDecoder": [], "codecs.StreamWriter": [], "codecs.StreamReader": [], "codecs.StreamReaderWriter": [], "codecs.StreamRecoder": [], "encodings": ["codecs", "encodings.CodecRegistryError"], "encodings.CodecRegistryError": [], "token": ["<builtin>.isinstance", "extend", "<builtin>.globals"], "<str>.replace": [], "tokenize.TokenInfo": ["<builtin>.property"], "tokenize.maybe": ["tokenize.group"], "tokenize.group": [], "tokenize._all_string_prefixes": [], "<builtin>.sorted": [], "tokenize.TokenError": [], "tokenize.StopTokenizing": [], "tokenize.Untokenizer": [], "traceback.FrameSummary": ["<builtin>.property"], "traceback.StackSummary": ["<builtin>.classmethod"], "traceback.TracebackException": ["<builtin>.classmethod"], "threading.Timer": [], "threading._MainThread": [], "threading._DummyThread": [], "threading._MainThread.__init__": ["threading.Event.set", "threading.Thread._set_native_id", "threading.Thread._set_tstate_lock", "threading.Thread.__init__", "threading.Thread._set_ident"], "threading.Thread.__init__": ["_weakrefset.WeakSet.add", "<builtin>.str", "threading.current_thread", "threading._make_invoke_excepthook", "threading._newname", "threading.Event.__init__"], "threading._newname": [], "threading.current_thread": ["_thread.get_ident", "threading._DummyThread.__init__"], "_thread.get_ident": [], "threading._DummyThread.__init__": ["threading.Thread._set_native_id", "threading._newname", "threading.Thread.__init__", "threading.Thread._set_ident"], "threading.Thread._set_ident": ["_thread.get_ident"], "threading.Thread._set_native_id": [], "threading.Event.__init__": ["threading.Condition.__init__"], "threading.Condition.__init__": ["threading.RLock", "_collections.deque"], "threading.RLock": ["threading._RLock.__init__", "_thread.RLock"], "threading._RLock.__init__": [], "_collections.deque": [], "threading._make_invoke_excepthook": ["<builtin>.RuntimeError"], "<builtin>.RuntimeError": [], "threading.Thread._set_tstate_lock": [], "threading.Event.set": [], "_threading_local": ["_threading_local.local", "contextlib", "contextlib.contextmanager", "threading", "_threading_local._localimpl", "weakref"], "weakref": ["weakref.WeakKeyDictionary", "weakref.finalize", "weakref.KeyedRef", "weakref.WeakValueDictionary", "weakref.WeakMethod", "_weakrefset"], "weakref.WeakMethod": [], "weakref.WeakValueDictionary": [], "weakref.KeyedRef": [], "weakref.WeakKeyDictionary": [], "weakref.finalize": ["<builtin>.classmethod", "<builtin>.property", "weakref.finalize._Info"], "weakref.finalize._Info": [], "_threading_local._localimpl": [], "_threading_local.local": [], "_bz2": [], "bz2.BZ2File": ["<builtin>.property"], "lzma": ["_compression", "os", "lzma.LZMAFile", "io", "_lzma"], "_lzma": [], "lzma.LZMAFile": ["<builtin>.property"], "grp": [], "shutil.Error": [], "shutil.SameFileError": [], "shutil.SpecialFileError": [], "shutil.ExecError": [], "shutil.ReadError": [], "shutil.RegistryError": [], "shutil._GiveupOnFastCopy": [], "gettext": ["<builtin>.enumerate", "locale", "gettext.GNUTranslations", "posixpath.join", "ntpath.join", "re", "gettext.NullTranslations", "os", "re.compile"], "locale": ["<builtin>.hasattr", "encodings", "<map>.items", "re", "<builtin>.globals", "<builtin>.sorted", "functools.wraps", "encodings.aliases", "re.compile", "functools", "<map>.setdefault"], "encodings.aliases": [], "<map>.setdefault": [], "posixpath.join": ["genericpath._check_arg_types", "posixpath._get_sep", "<builtin>.map", "os._fspath"], "os._fspath": ["<str>.format", "<builtin>.type", "<builtin>.isinstance", "<builtin>.hasattr", "<builtin>.TypeError"], "<str>.format": [], "posixpath._get_sep": ["<builtin>.isinstance"], "genericpath._check_arg_types": ["<builtin>.isinstance", "<builtin>.TypeError"], "ntpath.join": ["os._fspath", "<builtin>.isinstance", "genericpath._check_arg_types", "<builtin>.map", "ntpath.splitdrive"], "ntpath.splitdrive": ["os._fspath", "<builtin>.len", "<str>.replace", "<builtin>.isinstance", "<str>.find"], "gettext.NullTranslations": [], "gettext.GNUTranslations": [], "argparse._AttributeHolder": [], "argparse.HelpFormatter": ["argparse.HelpFormatter._Section"], "argparse.HelpFormatter._Section": [], "argparse.RawDescriptionHelpFormatter": [], "argparse.RawTextHelpFormatter": [], "argparse.ArgumentDefaultsHelpFormatter": [], "argparse.MetavarTypeHelpFormatter": [], "argparse.ArgumentError": [], "argparse.ArgumentTypeError": [], "argparse.Action": [], "argparse._StoreAction": [], "argparse._StoreConstAction": [], "argparse._StoreTrueAction": [], "argparse._StoreFalseAction": [], "argparse._AppendAction": [], "argparse._AppendConstAction": [], "argparse._CountAction": [], "argparse._HelpAction": [], "argparse._VersionAction": [], "argparse._SubParsersAction": ["argparse._SubParsersAction._ChoicesPseudoAction"], "argparse._SubParsersAction._ChoicesPseudoAction": [], "argparse._ExtendAction": [], "argparse.FileType": [], "argparse.Namespace": [], "argparse._ActionsContainer": [], "argparse._ArgumentGroup": [], "argparse._MutuallyExclusiveGroup": [], "argparse.ArgumentParser": [], "sqlparse": ["sqlparse.filters", "sqlparse.tokens", "sqlparse.formatter", "sqlparse.sql", "sqlparse.cli", "sqlparse.engine"], "sqlparse.engine": ["sqlparse.engine.grouping", "sqlparse.engine.filter_stack", "sqlparse.engine.statement_splitter"], "sqlparse.engine.grouping": ["sqlparse.utils.recurse", "sqlparse.utils.recurse.wrap", "sqlparse.tokens", "sqlparse.sql", "sqlparse.utils"], "sqlparse.utils.recurse": [], "sqlparse.utils.recurse.wrap": [], "sqlparse.engine.filter_stack": ["sqlparse.lexer", "sqlparse.engine.filter_stack.FilterStack", "sqlparse.engine.grouping", "sqlparse.engine.statement_splitter"], "sqlparse.engine.statement_splitter": ["sqlparse.engine.statement_splitter.StatementSplitter", "sqlparse.sql", "sqlparse.tokens"], "sqlparse.engine.statement_splitter.StatementSplitter": [], "sqlparse.engine.filter_stack.FilterStack": [], "sqlparse.__main__": ["sqlparse.cli", "sqlparse.cli.main"], "sqlparse.cli.main": ["sqlparse.formatter.validate_options", "_io.TextIOWrapper", "<builtin>.vars", "sqlparse.format", "<builtin>.open", "sqlparse.cli._error", "sqlparse.cli.create_parser", "argparse.ArgumentParser.parse_args"], "sqlparse.cli.create_parser": ["argparse._ActionsContainer.add_argument", "argparse.ArgumentParser.__init__", "argparse._ActionsContainer.add_argument_group"], "argparse.ArgumentParser.__init__": ["argparse._ActionsContainer.add_argument", "argparse._ActionsContainer._add_container_actions", "posixpath.basename", "<builtin>.super", "gettext.gettext", "ntpath.basename", "argparse._ActionsContainer.add_argument_group", "argparse._ActionsContainer.register"], "posixpath.basename": ["posixpath._get_sep", "os._fspath"], "ntpath.basename": ["ntpath.split"], "ntpath.split": ["ntpath._get_bothseps", "ntpath.splitdrive", "os._fspath", "<builtin>.len"], "ntpath._get_bothseps": ["<builtin>.isinstance"], "gettext.gettext": ["gettext.dgettext"], "gettext.dgettext": ["<map>.get", "gettext.NullTranslations.gettext", "gettext.translation"], "<map>.get": [], "gettext.translation": ["ntpath.abspath", "gettext.NullTranslations.__init__", "warnings.catch_warnings.__init__", "warnings.warn", "<builtin>.FileNotFoundError", "<builtin>.open", "copy", "<map>.get", "posixpath.abspath", "copy.copy", "warnings", "gettext.find", "<map>.setdefault"], "gettext.find": ["gettext._expand_lang", "append", "posixpath.join", "ntpath.join", "genericpath.exists"], "gettext._expand_lang": ["append", "reverse", "locale.normalize", "<builtin>.range"], "locale.normalize": ["locale._replace_encoding", "<map>.get", "<str>.replace", "locale._append_modifier"], "locale._append_modifier": ["locale._replace_encoding"], "locale._replace_encoding": ["<map>.get", "encodings.normalize_encoding", "<str>.lower", "<str>.replace"], "encodings.normalize_encoding": ["<builtin>.isinstance", "<builtin>.str", "append"], "<str>.lower": [], "reverse": [], "genericpath.exists": [], "gettext.NullTranslations.__init__": ["gettext.NullTranslations._parse"], "gettext.NullTranslations._parse": [], "<builtin>.FileNotFoundError": [], "posixpath.abspath": ["os._fspath", "posixpath.join", "posixpath.isabs", "<builtin>.isinstance", "posixpath.normpath"], "posixpath.isabs": ["posixpath._get_sep", "os._fspath", "<str>.startswith"], "posixpath.normpath": ["pop", "append", "os._fspath", "<str>.startswith", "<builtin>.isinstance", "<str>.split"], "pop": [], "ntpath.abspath": [], "<builtin>.open": [], "copy": ["<builtin>.type", "copyreg", "<builtin>.getattr", "copy.Error", "types", "weakref"], "copy.Error": [], "copy.copy": ["<builtin>.type", "<map>", "copy._copy_immutable", "<builtin>.issubclass", "<builtin>.isinstance", "<map>.get", "<builtin>.getattr", "copy._reconstruct"], "<map>": [], "copy._copy_immutable": [], "copy._reconstruct": ["<builtin>.len", "copy.deepcopy", "<builtin>.setattr", "<builtin>.isinstance", "<builtin>.id", "<builtin>.hasattr"], "copy.deepcopy": ["<builtin>.type", "copy._keep_alive", "<map>", "copy._deepcopy_atomic", "<builtin>.issubclass", "<builtin>.id", "<builtin>.isinstance", "<map>.get", "<builtin>.getattr", "copy._reconstruct"], "<builtin>.id": [], "copy._deepcopy_atomic": [], "copy._keep_alive": ["<builtin>.id"], "<builtin>.setattr": [], "warnings.warn": ["<builtin>.type", "warnings._is_internal_frame", "warnings.warn_explicit", "<builtin>.issubclass", "<builtin>.isinstance", "<builtin>.range", "warnings._next_external_frame", "<builtin>.TypeError"], "warnings._is_internal_frame": [], "warnings._next_external_frame": ["warnings._is_internal_frame"], "warnings.warn_explicit": ["<builtin>.int", "<builtin>.str", "linecache", "<builtin>.RuntimeError", "warnings._showwarnmsg", "<builtin>.issubclass", "<builtin>.isinstance", "<map>.clear", "warnings.WarningMessage.__init__", "<map>.get", "<str>.lower", "linecache.getlines"], "<map>.clear": [], "linecache.getlines": ["linecache.clearcache", "<builtin>.len", "linecache.updatecache"], "linecache.updatecache": ["<builtin>.len", "posixpath.join", "ntpath.join", "linecache.lazycache", "<str>.startswith", "ntpath.isabs", "posixpath.isabs", "<str>.endswith", "tokenize.open"], "<str>.startswith": [], "<str>.endswith": [], "linecache.lazycache": ["<builtin>.getattr", "<builtin>.len", "<str>.startswith", "<str>.endswith"], "ntpath.isabs": ["os._fspath", "<builtin>.len", "<str>.replace", "<str>.startswith", "<builtin>.isinstance", "ntpath._get_bothseps", "ntpath.splitdrive"], "<str>.find": [], "tokenize.open": ["builtins.open", "_io.TextIOWrapper", "tokenize.detect_encoding"], "builtins.open": [], "tokenize.detect_encoding": ["tokenize.detect_encoding.read_or_stop", "tokenize.detect_encoding.find_cookie"], "tokenize.detect_encoding.read_or_stop": [], "tokenize.detect_encoding.find_cookie": ["tokenize._get_normal_name", "<builtin>.SyntaxError"], "<builtin>.SyntaxError": [], "tokenize._get_normal_name": ["<str>.lower", "<str>.replace", "<str>.startswith"], "_io.TextIOWrapper": [], "linecache.clearcache": [], "warnings.WarningMessage.__init__": [], "warnings._showwarnmsg": ["warnings._showwarnmsg_impl"], "warnings._showwarnmsg_impl": ["warnings._formatwarnmsg"], "warnings._formatwarnmsg": ["warnings._formatwarnmsg_impl"], "warnings._formatwarnmsg_impl": ["linecache.getline", "linecache", "tracemalloc", "<str>.strip"], "linecache.getline": ["linecache.getlines", "<builtin>.len"], "tracemalloc": ["linecache", "pickle", "tracemalloc.Frame", "tracemalloc.Filter", "collections.abc", "fnmatch", "tracemalloc._Traces", "posixpath", "tracemalloc.BaseFilter", "tracemalloc.StatisticDiff", "tracemalloc.Trace", "tracemalloc.DomainFilter", "tracemalloc.Snapshot", "tracemalloc.Traceback", "tracemalloc.Statistic", "functools"], "collections.abc": ["collections.abc"], "pickle": ["append", "pickle._Pickler", "_compat_pickle", "pickle._Framer", "pickle._Stop", "codecs", "pickle.PickleError", "pickle._Unpickler", "re", "_pickle", "types", "functools", "struct", "pickle.PicklingError", "extend", "io", "pickle.UnpicklingError", "copyreg", "pickle._Unframer"], "struct": ["_struct"], "_struct": [], "_compat_pickle": ["<map>.update", "<builtin>.dict", "<map>.items", "<builtin>.len"], "<map>.update": [], "_pickle": [], "pickle.PickleError": [], "pickle.PicklingError": [], "pickle.UnpicklingError": [], "pickle._Stop": [], "pickle._Framer": [], "pickle._Unframer": [], "pickle._Pickler": ["<builtin>.type"], "pickle._Unpickler": [], "tracemalloc.Statistic": [], "tracemalloc.StatisticDiff": [], "tracemalloc.Frame": ["<builtin>.property"], "tracemalloc.Traceback": [], "tracemalloc.Trace": ["<builtin>.property"], "tracemalloc._Traces": [], "tracemalloc.BaseFilter": [], "tracemalloc.Filter": ["<builtin>.property"], "tracemalloc.DomainFilter": ["<builtin>.property"], "tracemalloc.Snapshot": ["<builtin>.staticmethod"], "warnings.catch_warnings.__init__": [], "gettext.NullTranslations.gettext": [], "argparse._ActionsContainer.add_argument_group": ["argparse._ArgumentGroup.__init__"], "argparse._ArgumentGroup.__init__": ["<builtin>.super"], "argparse._ActionsContainer.register": [], "argparse._ActionsContainer.add_argument": ["<builtin>.ValueError", "argparse._ActionsContainer._get_optional_kwargs", "<builtin>.len", "argparse._ActionsContainer._registry_get", "argparse.ArgumentParser._add_action", "argparse._ActionsContainer._get_positional_kwargs", "argparse._ActionsContainer._add_action", "argparse._ActionsContainer._pop_action_class", "<builtin>.hasattr", "argparse.ArgumentParser._get_formatter", "<builtin>.callable"], "argparse._ActionsContainer._get_optional_kwargs": ["<builtin>.ValueError", "append", "<builtin>.dict", "<builtin>.len", "gettext.gettext"], "argparse._ActionsContainer._get_positional_kwargs": ["<builtin>.dict", "<builtin>.TypeError", "gettext.gettext"], "argparse._ActionsContainer._pop_action_class": ["argparse._ActionsContainer._registry_get"], "argparse._ActionsContainer._registry_get": [], "argparse.ArgumentParser._get_formatter": [], "argparse._ActionsContainer._add_action": ["argparse._ActionsContainer._check_conflict"], "argparse._ActionsContainer._check_conflict": ["append", "argparse._ActionsContainer._get_handler"], "argparse._ActionsContainer._get_handler": ["<builtin>.ValueError", "<builtin>.getattr", "gettext.gettext"], "argparse.ArgumentParser._add_action": [], "argparse._ActionsContainer._add_container_actions": ["<builtin>.ValueError", "gettext.gettext", "argparse._ActionsContainer.add_mutually_exclusive_group", "argparse._ActionsContainer.add_argument_group", "<map>.get"], "argparse._ActionsContainer.add_mutually_exclusive_group": ["argparse._MutuallyExclusiveGroup.__init__"], "argparse._MutuallyExclusiveGroup.__init__": ["<builtin>.super"], "argparse.ArgumentParser.parse_args": ["argparse.ArgumentParser.error", "argparse.ArgumentParser.parse_known_args", "gettext.gettext"], "argparse.ArgumentParser.parse_known_args": ["<builtin>.str", "argparse.ArgumentParser._parse_known_args", "<builtin>.setattr", "argparse.Namespace.__init__", "<builtin>.delattr", "<builtin>.list", "<builtin>.getattr", "argparse.ArgumentParser.error", "<builtin>.hasattr"], "argparse.Namespace.__init__": ["<builtin>.setattr"], "argparse.ArgumentParser._parse_known_args": ["append", "<builtin>.max", "<builtin>.min", "<builtin>.iter", "gettext.gettext", "argparse.ArgumentParser.error", "<map>.setdefault", "argparse.ArgumentParser._parse_optional", "argparse.ArgumentParser._get_value", "argparse.ArgumentParser._read_args_from_files", "<builtin>.set", "<builtin>.isinstance", "extend", "<builtin>.enumerate", "argparse.ArgumentParser._get_positional_actions", "<builtin>.setattr", "argparse.ArgumentParser._parse_known_args.consume_optional", "argparse.ArgumentParser._parse_known_args.consume_positionals", "<builtin>.getattr", "<builtin>.hasattr"], "argparse.ArgumentParser._read_args_from_files": ["<builtin>.str", "argparse.ArgumentParser.convert_arg_line_to_args", "append", "<builtin>.open", "argparse.ArgumentParser._read_args_from_files", "extend", "argparse.ArgumentParser.error"], "argparse.ArgumentParser.convert_arg_line_to_args": [], "argparse.ArgumentParser.error": ["argparse.ArgumentParser.exit", "argparse.ArgumentParser.print_usage", "gettext.gettext"], "argparse.ArgumentParser.print_usage": ["argparse.ArgumentParser.format_usage", "argparse.ArgumentParser._print_message"], "argparse.ArgumentParser.format_usage": ["argparse.ArgumentParser._get_formatter"], "argparse.ArgumentParser._print_message": [], "argparse.ArgumentParser.exit": ["argparse.ArgumentParser._print_message"], "argparse.ArgumentParser._parse_optional": ["argparse.ArgumentParser._get_option_tuples", "argparse.ArgumentParser.error", "<builtin>.len", "gettext.gettext"], "argparse.ArgumentParser._get_option_tuples": ["argparse.ArgumentParser.error", "append", "gettext.gettext"], "argparse.ArgumentParser._get_positional_actions": [], "argparse.ArgumentParser._parse_known_args.consume_positionals": ["<builtin>.zip", "<builtin>.len", "argparse.ArgumentParser._match_arguments_partial", "argparse.ArgumentParser._parse_known_args.take_action"], "argparse.ArgumentParser._match_arguments_partial": ["<builtin>.len", "argparse.ArgumentParser._get_nargs_pattern", "re.match", "<builtin>.range", "extend"], "argparse.ArgumentParser._get_nargs_pattern": ["<str>.replace"], "re.match": ["re._compile"], "argparse.ArgumentParser._parse_known_args.take_action": ["argparse.ArgumentParser._get_values", "argparse._get_action_name", "gettext.gettext", "<map>.get", "argparse.ArgumentError.__init__"], "argparse.ArgumentParser._get_values": ["argparse.ArgumentParser._check_value", "<builtin>.len", "remove", "<builtin>.isinstance", "argparse.ArgumentParser._get_value"], "argparse.ArgumentParser._get_value": ["<builtin>.repr", "<builtin>.str", "argparse._ActionsContainer._registry_get", "gettext.gettext", "<builtin>.callable", "<builtin>.getattr", "argparse.ArgumentError.__init__"], "argparse.ArgumentError.__init__": ["argparse._get_action_name"], "argparse._get_action_name": [], "argparse.ArgumentParser._check_value": ["<builtin>.map", "argparse.ArgumentError.__init__", "gettext.gettext"], "argparse.ArgumentParser._parse_known_args.consume_optional": ["append", "argparse.ArgumentParser._match_argument", "gettext.gettext", "argparse.ArgumentParser._parse_known_args.take_action", "argparse.ArgumentError.__init__"], "argparse.ArgumentParser._match_argument": ["<builtin>.len", "argparse.ArgumentParser._get_nargs_pattern", "gettext.gettext", "re.match", "<map>.get", "gettext.ngettext", "argparse.ArgumentError.__init__"], "gettext.ngettext": ["gettext.dngettext"], "gettext.dngettext": ["<map>.get", "gettext.NullTranslations.ngettext", "gettext.translation"], "gettext.NullTranslations.ngettext": [], "<builtin>.delattr": [], "sqlparse.cli._error": [], "<builtin>.vars": [], "sqlparse.formatter.validate_options": ["<builtin>.int"], "sqlparse.format": ["append", "sqlparse.formatter.validate_options", "sqlparse.engine.filter_stack.FilterStack.run", "sqlparse.engine.filter_stack.FilterStack.__init__", "sqlparse.formatter.build_filter_stack"], "sqlparse.engine.filter_stack.FilterStack.__init__": [], "sqlparse.formatter.build_filter_stack": ["append", "sqlparse.engine.filter_stack.FilterStack.enable_grouping"], "sqlparse.engine.filter_stack.FilterStack.enable_grouping": [], "sqlparse.engine.filter_stack.FilterStack.run": ["sqlparse.engine.grouping.group", "sqlparse.lexer.tokenize", "sqlparse.engine.statement_splitter.StatementSplitter.__init__", "sqlparse.engine.statement_splitter.StatementSplitter.process"], "sqlparse.lexer.tokenize": ["sqlparse.lexer.Lexer.get_tokens"], "sqlparse.lexer.Lexer.get_tokens": ["<builtin>.enumerate", "<builtin>.type", "sqlparse.utils.consume", "<builtin>.isinstance", "<builtin>.TypeError", "<builtin>.callable"], "sqlparse.utils.consume": ["_collections.deque"], "sqlparse.engine.statement_splitter.StatementSplitter.__init__": ["sqlparse.engine.statement_splitter.StatementSplitter._reset"], "sqlparse.engine.statement_splitter.StatementSplitter._reset": [], "sqlparse.engine.statement_splitter.StatementSplitter.process": ["sqlparse.engine.statement_splitter.StatementSplitter._reset", "append", "<builtin>.all", "sqlparse.engine.statement_splitter.StatementSplitter._change_splitlevel"], "sqlparse.engine.statement_splitter.StatementSplitter._change_splitlevel": ["<builtin>.max"], "<builtin>.all": [], "sqlparse.engine.grouping.group": [], "sqlparse.engine.grouping._group_matching": ["<builtin>.enumerate", "pop", "append", "<builtin>.isinstance", "<builtin>.list", "sqlparse.engine.grouping._group_matching"], "sqlparse.engine.grouping.group_brackets": ["sqlparse.engine.grouping._group_matching"], "sqlparse.engine.grouping.group_parenthesis": ["sqlparse.engine.grouping._group_matching"], "sqlparse.engine.grouping.group_case": ["sqlparse.engine.grouping._group_matching"], "sqlparse.engine.grouping.group_if": ["sqlparse.engine.grouping._group_matching"], "sqlparse.engine.grouping.group_for": ["sqlparse.engine.grouping._group_matching"], "sqlparse.engine.grouping.group_begin": ["sqlparse.engine.grouping._group_matching"], "sqlparse.engine.grouping.group_typecasts": ["sqlparse.engine.grouping._group"], "sqlparse.engine.grouping._group": ["sqlparse.engine.grouping.<lambda1>", "sqlparse.engine.grouping.group_tzcasts.valid_prev", "sqlparse.engine.grouping.group_tzcasts.match", "sqlparse.engine.grouping.group_comparison.post", "sqlparse.engine.grouping.group_as.match", "sqlparse.engine.grouping.group_as.valid_next", "sqlparse.engine.grouping.group_as.post", "sqlparse.engine.grouping.group_operator.valid", "<builtin>.list", "sqlparse.engine.grouping.group_typecasts.post", "sqlparse.engine.grouping.group_operator.post", "sqlparse.engine.grouping.group_identifier_list.valid", "sqlparse.engine.grouping.group_arrays.valid_prev", "sqlparse.engine.grouping.group_operator.match", "sqlparse.engine.grouping.group_identifier_list.post", "sqlparse.engine.grouping.group_tzcasts.valid_next", "sqlparse.engine.grouping.group_typed_literal.post", "sqlparse.engine.grouping.group_identifier_list.match", "sqlparse.engine.grouping.group_comparison.match", "sqlparse.engine.grouping._group", "sqlparse.engine.grouping.group_arrays.post", "sqlparse.engine.grouping.group_typed_literal.valid_prev", "sqlparse.engine.grouping.group_typed_literal.match_to_extend", "<builtin>.isinstance", "sqlparse.engine.grouping.group_typed_literal.match", "sqlparse.engine.grouping.group_typecasts.valid", "sqlparse.engine.grouping.group_period.valid_next", "sqlparse.engine.grouping.group_typed_literal.valid_next", "sqlparse.engine.grouping.group_assignment.post", "sqlparse.engine.grouping.group_arrays.valid_next", "sqlparse.engine.grouping.group_arrays.match", "sqlparse.engine.grouping.group_tzcasts.post", "sqlparse.engine.grouping.group_comparison.valid", "<builtin>.enumerate", "sqlparse.engine.grouping.group_period.match", "sqlparse.engine.grouping.group_typecasts.match", "sqlparse.engine.grouping.group_as.valid_prev", "sqlparse.engine.grouping.group_typed_literal.valid_final", "sqlparse.engine.grouping.group_period.valid_prev", "sqlparse.engine.grouping.group_assignment.match", "sqlparse.engine.grouping.group_assignment.valid", "sqlparse.engine.grouping.group_period.post", "sqlparse.engine.grouping.<lambda2>"], "sqlparse.engine.grouping.group_typecasts.match": [], "sqlparse.engine.grouping.<lambda1>": [], "sqlparse.engine.grouping.group_typecasts.valid": [], "sqlparse.engine.grouping.<lambda2>": [], "sqlparse.engine.grouping.group_typecasts.post": [], "sqlparse.engine.grouping.group_tzcasts": ["sqlparse.engine.grouping._group"], "sqlparse.engine.grouping.group_tzcasts.match": [], "sqlparse.engine.grouping.group_tzcasts.valid_prev": [], "sqlparse.engine.grouping.group_tzcasts.valid_next": [], "sqlparse.engine.grouping.group_tzcasts.post": [], "sqlparse.engine.grouping.group_typed_literal": ["sqlparse.engine.grouping._group"], "sqlparse.engine.grouping.group_typed_literal.match": ["sqlparse.utils.imt"], "sqlparse.utils.imt": ["<builtin>.isinstance", "<builtin>.any"], "sqlparse.engine.grouping.group_typed_literal.valid_prev": [], "sqlparse.engine.grouping.group_typed_literal.valid_next": [], "sqlparse.engine.grouping.group_typed_literal.post": [], "sqlparse.engine.grouping.group_typed_literal.match_to_extend": ["<builtin>.isinstance"], "sqlparse.engine.grouping.group_typed_literal.valid_final": [], "sqlparse.engine.grouping.group_period": ["sqlparse.engine.grouping._group"], "sqlparse.engine.grouping.group_period.match": [], "sqlparse.engine.grouping.group_period.valid_prev": ["sqlparse.utils.imt"], "sqlparse.engine.grouping.group_period.valid_next": [], "sqlparse.engine.grouping.group_period.post": ["sqlparse.utils.imt"], "sqlparse.engine.grouping.group_as": ["sqlparse.engine.grouping._group"], "sqlparse.engine.grouping.group_as.match": [], "sqlparse.engine.grouping.group_as.valid_prev": [], "sqlparse.engine.grouping.group_as.valid_next": ["sqlparse.utils.imt"], "sqlparse.engine.grouping.group_as.post": [], "sqlparse.engine.grouping.group_assignment": ["sqlparse.engine.grouping._group"], "sqlparse.engine.grouping.group_assignment.match": [], "sqlparse.engine.grouping.group_assignment.valid": [], "sqlparse.engine.grouping.group_assignment.post": [], "sqlparse.engine.grouping.group_comparison": ["sqlparse.engine.grouping._group"], "sqlparse.engine.grouping.group_comparison.match": [], "sqlparse.engine.grouping.group_comparison.valid": ["sqlparse.utils.imt"], "sqlparse.engine.grouping.group_comparison.post": [], "sqlparse.engine.grouping.group_arrays": ["sqlparse.engine.grouping._group"], "sqlparse.engine.grouping.group_arrays.match": ["<builtin>.isinstance"], "sqlparse.engine.grouping.group_arrays.valid_prev": ["sqlparse.utils.imt"], "sqlparse.engine.grouping.group_arrays.valid_next": [], "sqlparse.engine.grouping.group_arrays.post": [], "sqlparse.engine.grouping.group_operator": ["sqlparse.engine.grouping._group"], "sqlparse.engine.grouping.group_operator.match": ["sqlparse.utils.imt"], "sqlparse.engine.grouping.group_operator.valid": ["sqlparse.utils.imt"], "sqlparse.engine.grouping.group_operator.post": [], "sqlparse.engine.grouping.group_identifier_list": ["sqlparse.engine.grouping._group"], "sqlparse.engine.grouping.group_identifier_list.match": [], "sqlparse.engine.grouping.group_identifier_list.valid": ["sqlparse.utils.imt"], "sqlparse.engine.grouping.group_identifier_list.post": [], "sqlparse.engine.grouping.group_aliased": ["<builtin>.isinstance"], "sqlparse.engine.grouping.group_functions": ["<builtin>.isinstance"], "sqlparse.engine.grouping.group_order": ["sqlparse.utils.imt"], "sqlparse.engine.grouping.align_comments": ["<builtin>.isinstance"], "sqlparse.engine.grouping.group_values": ["<builtin>.isinstance"], "sqlparse.sql.NameAliasMixin.get_alias": ["<builtin>.len"], "sqlparse.sql.Token.__init__": ["<builtin>.str", "<str>.upper"], "sqlparse.sql.Token.__repr__": ["<builtin>.locals", "sqlparse.sql.Token._get_repr_value", "<str>.startswith", "<builtin>.id", "sqlparse.sql.Token._get_repr_name", "<str>.endswith"], "sqlparse.sql.Token._get_repr_name": ["<builtin>.str"], "sqlparse.sql.Token._get_repr_value": ["re.sub", "<builtin>.str", "<builtin>.len"], "re.sub": ["re._compile"], "<builtin>.locals": [], "sqlparse.sql.Token.match": ["<builtin>.isinstance", "re.compile"], "sqlparse.sql.Token.within": ["<builtin>.isinstance"], "sqlparse.sql.TokenList.__init__": ["<builtin>.str", "<builtin>.super", "<builtin>.setattr"], "sqlparse.sql.TokenList.__str__": ["sqlparse.sql.TokenList.flatten"], "sqlparse.sql.TokenList.flatten": [], "sqlparse.sql.TokenList.__iter__": ["<builtin>.iter"], "sqlparse.sql.TokenList._get_repr_name": ["<builtin>.type"], "sqlparse.sql.TokenList._pprint_tree": ["<builtin>.enumerate", "<builtin>.locals", "<builtin>.len", "<builtin>.print"], "sqlparse.sql.TokenList.get_token_at_offset": ["<builtin>.len", "sqlparse.sql.TokenList.flatten"], "sqlparse.sql.TokenList._token_matching": ["<builtin>.isinstance", "<builtin>.len", "<builtin>.range"], "sqlparse.sql.TokenList.token_first": ["sqlparse.sql.TokenList._token_matching"], "sqlparse.sql.TokenList.token_next_by": ["sqlparse.sql.TokenList._token_matching"], "sqlparse.sql.TokenList.token_not_matching": ["<builtin>.isinstance", "sqlparse.sql.TokenList._token_matching"], "sqlparse.sql.TokenList.token_matching": ["sqlparse.sql.TokenList._token_matching"], "sqlparse.sql.TokenList.token_prev": ["sqlparse.sql.TokenList.token_next"], "sqlparse.sql.TokenList.token_next": ["sqlparse.sql.TokenList._token_matching"], "sqlparse.sql.TokenList.token_index": ["<builtin>.isinstance", "sqlparse.sql.TokenList.token_index"], "sqlparse.sql.TokenList.group_tokens": ["<builtin>.isinstance", "<builtin>.str"], "sqlparse.sql.TokenList.insert_before": ["<builtin>.isinstance", "sqlparse.sql.TokenList.token_index"], "sqlparse.sql.TokenList.insert_after": ["<builtin>.isinstance", "sqlparse.sql.TokenList.token_index", "sqlparse.sql.TokenList.token_next"], "sqlparse.sql.TokenList.has_alias": ["sqlparse.sql.TokenList.get_alias"], "sqlparse.sql.TokenList.get_alias": [], "sqlparse.sql.TokenList.get_name": ["sqlparse.sql.TokenList.get_alias", "sqlparse.sql.TokenList.get_real_name"], "sqlparse.sql.TokenList.get_real_name": [], "sqlparse.sql.TokenList.get_parent_name": ["sqlparse.sql.TokenList.token_prev", "sqlparse.sql.TokenList.token_next_by", "sqlparse.utils.remove_quotes"], "sqlparse.utils.remove_quotes": [], "sqlparse.sql.TokenList._get_first_name": ["<builtin>.isinstance", "append", "<builtin>.reversed", "sqlparse.utils.remove_quotes"], "sqlparse.sql.Statement.get_type": ["sqlparse.sql.TokenList.token_first", "<builtin>.isinstance", "sqlparse.sql.TokenList.token_index", "sqlparse.sql.TokenList.token_next"], "sqlparse.sql.Identifier.is_wildcard": ["sqlparse.sql.TokenList.token_next_by"], "sqlparse.sql.Identifier.get_typecast": ["sqlparse.sql.TokenList.token_next_by", "sqlparse.sql.TokenList.token_next"], "sqlparse.sql.Identifier.get_ordering": ["sqlparse.sql.TokenList.token_next_by"], "sqlparse.sql.Identifier.get_array_indices": ["<builtin>.isinstance"], "sqlparse.sql.Case.get_cases": ["append"], "sqlparse.sql.Function.get_parameters": ["sqlparse.utils.imt", "<builtin>.isinstance"], "sqlparse.filters.reindent.ReindentFilter._flatten_up_to_token": ["<builtin>.next"], "sqlparse.filters.reindent.ReindentFilter._get_offset": ["<builtin>.map", "<builtin>.len", "sqlparse.filters.reindent.ReindentFilter._flatten_up_to_token"], "sqlparse.filters.reindent.ReindentFilter.nl": ["sqlparse.sql.Token.__init__", "<builtin>.max"], "<str>.upper": [], "sqlparse.filters.reindent.ReindentFilter._next_token": ["sqlparse.filters.reindent.ReindentFilter._next_token"], "sqlparse.filters.reindent.ReindentFilter._split_kwds": ["<builtin>.str", "sqlparse.filters.reindent.ReindentFilter._next_token", "sqlparse.filters.reindent.ReindentFilter.nl"], "sqlparse.filters.reindent.ReindentFilter._split_statements": ["sqlparse.filters.reindent.ReindentFilter.nl"], "sqlparse.filters.reindent.ReindentFilter._process": ["<builtin>.type", "<builtin>.getattr"], "sqlparse.filters.reindent.ReindentFilter._process_where": ["sqlparse.filters.reindent.ReindentFilter.nl"], "sqlparse.filters.reindent.ReindentFilter._process_function": ["sqlparse.filters.reindent.ReindentFilter._process_default"], "sqlparse.filters.reindent.ReindentFilter._process_default": ["sqlparse.filters.reindent.ReindentFilter._split_kwds", "sqlparse.filters.reindent.ReindentFilter._split_statements", "sqlparse.filters.reindent.ReindentFilter._process"], "sqlparse.filters.reindent.ReindentFilter._process_identifierlist": ["<builtin>.next", "<builtin>.len", "<builtin>.sum", "sqlparse.sql.Token.__init__", "sqlparse.filters.reindent.ReindentFilter._process_default", "<builtin>.list", "sqlparse.filters.reindent.ReindentFilter._get_offset"], "<builtin>.sum": [], "sqlparse.filters.reindent.ReindentFilter._process_case": ["<builtin>.next", "sqlparse.filters.reindent.ReindentFilter._get_offset", "<builtin>.iter"], "sqlparse.filters.reindent.ReindentFilter._process_values": ["sqlparse.filters.reindent.ReindentFilter.nl", "sqlparse.filters.reindent.ReindentFilter._get_offset"], "sqlparse.filters.reindent.ReindentFilter.process": ["sqlparse.sql.Token.__init__", "<builtin>.str", "sqlparse.filters.reindent.ReindentFilter._process"], "sqlparse.tokens._TokenType.__contains__": ["<builtin>.len"], "sqlparse.tokens._TokenType.__getattr__": ["<builtin>.setattr"], "sqlparse.keywords.is_keyword": ["<map>.get"], "sqlparse.filters.output.OutputFilter.process": ["sqlparse.filters.output.OutputFilter._process", "<builtin>.str", "<builtin>.len"], "sqlparse.filters.output.OutputFilter._process": [], "sqlparse.filters.output.OutputPythonFilter._process": ["sqlparse.sql.Token.__init__", "<builtin>.len"], "sqlparse.filters.output.OutputPHPFilter._process": ["sqlparse.sql.Token.__init__"], "sqlparse.filters.aligned_indent.AlignedIndentFilter.__init__": ["<builtin>.len"], "sqlparse.filters.aligned_indent.AlignedIndentFilter.nl": ["sqlparse.sql.Token.__init__", "<builtin>.isinstance", "<builtin>.len"], "sqlparse.filters.aligned_indent.AlignedIndentFilter._process_statement": ["sqlparse.sql.TokenList.__init__", "<builtin>.len", "sqlparse.filters.aligned_indent.AlignedIndentFilter._process"], "sqlparse.filters.aligned_indent.AlignedIndentFilter._process": ["<builtin>.type", "<builtin>.getattr"], "sqlparse.filters.aligned_indent.AlignedIndentFilter._process_parenthesis": ["sqlparse.filters.aligned_indent.AlignedIndentFilter.nl"], "sqlparse.filters.aligned_indent.AlignedIndentFilter._process_identifierlist": ["<builtin>.list", "sqlparse.filters.aligned_indent.AlignedIndentFilter.nl", "sqlparse.filters.aligned_indent.AlignedIndentFilter._process_default"], "sqlparse.filters.aligned_indent.AlignedIndentFilter._process_default": ["sqlparse.filters.aligned_indent.AlignedIndentFilter._split_kwds"], "sqlparse.filters.aligned_indent.AlignedIndentFilter._split_kwds": ["<builtin>.str", "sqlparse.filters.aligned_indent.AlignedIndentFilter._next_token", "sqlparse.filters.aligned_indent.AlignedIndentFilter.nl"], "sqlparse.filters.aligned_indent.AlignedIndentFilter._next_token": ["sqlparse.filters.aligned_indent.AlignedIndentFilter._next_token"], "sqlparse.filters.aligned_indent.AlignedIndentFilter._process_case": ["<builtin>.enumerate", "<builtin>.str", "<builtin>.len", "<builtin>.max", "sqlparse.filters.aligned_indent.AlignedIndentFilter.nl", "sqlparse.sql.Token.__init__", "<builtin>.map"], "sqlparse.filters.aligned_indent.AlignedIndentFilter.process": ["sqlparse.filters.aligned_indent.AlignedIndentFilter._process"], "sqlparse.filters.right_margin.RightMarginFilter._process": ["re.search", "<builtin>.str", "<builtin>.type", "<builtin>.len", "sqlparse.sql.Token.__init__", "sqlparse.filters.right_margin.RightMarginFilter._process"], "re.search": ["re._compile"], "sqlparse.utils.split_unquoted_newlines": ["<builtin>.str", "append", "<str>.split"], "sqlparse.utils.recurse.wrap.wrapped_f": ["sqlparse.engine.grouping.group_comments", "sqlparse.engine.grouping.group_identifier", "sqlparse.engine.grouping.group_functions", "<builtin>.isinstance", "sqlparse.engine.grouping.group_where", "sqlparse.engine.grouping.group_aliased", "sqlparse.utils.recurse.wrap.wrapped_f", "sqlparse.engine.grouping.align_comments"], "sqlparse.engine.grouping.group_comments": [], "sqlparse.engine.grouping.group_identifier": [], "sqlparse.engine.grouping.group_where": [], "sqlparse.parse": ["sqlparse.parsestream", "<builtin>.tuple"], "sqlparse.parsestream": ["sqlparse.engine.filter_stack.FilterStack.__init__", "sqlparse.engine.filter_stack.FilterStack.enable_grouping", "sqlparse.engine.filter_stack.FilterStack.run"], "sqlparse.split": ["<builtin>.str", "sqlparse.engine.filter_stack.FilterStack.__init__", "sqlparse.engine.filter_stack.FilterStack.run"], "sqlparse.filters.others.StripCommentsFilter._process": ["sqlparse.filters.others.StripCommentsFilter._process._get_insert_token", "sqlparse.filters.others.StripCommentsFilter._process.get_next_comment"], "sqlparse.filters.others.StripCommentsFilter._process.get_next_comment": [], "sqlparse.filters.others.StripCommentsFilter._process._get_insert_token": ["re.search", "sqlparse.sql.Token.__init__"], "sqlparse.filters.others.StripCommentsFilter.process": ["sqlparse.filters.others.StripCommentsFilter.process", "sqlparse.filters.others.StripCommentsFilter._process"], "sqlparse.filters.others.StripWhitespaceFilter._stripws": ["<builtin>.type", "<builtin>.getattr"], "sqlparse.filters.others.StripWhitespaceFilter._stripws_identifierlist": ["sqlparse.filters.others.StripWhitespaceFilter._stripws_default", "<builtin>.list"], "sqlparse.filters.others.StripWhitespaceFilter._stripws_default": [], "sqlparse.filters.others.StripWhitespaceFilter._stripws_parenthesis": ["sqlparse.filters.others.StripWhitespaceFilter._stripws_default"], "sqlparse.filters.others.StripWhitespaceFilter.process": ["sqlparse.filters.others.StripWhitespaceFilter._stripws", "sqlparse.filters.others.StripWhitespaceFilter.process"], "sqlparse.filters.others.SpacesAroundOperatorsFilter._process": ["sqlparse.sql.Token.__init__"], "sqlparse.filters.others.SpacesAroundOperatorsFilter.process": ["sqlparse.filters.others.SpacesAroundOperatorsFilter._process", "sqlparse.filters.others.SpacesAroundOperatorsFilter.process"], "sqlparse.filters.others.SerializerUnicode.process": ["sqlparse.utils.split_unquoted_newlines"], "sqlparse.filters.tokens._CaseFilter.__init__": ["<builtin>.getattr"], "sqlparse.filters.tokens.TruncateStringFilter.process": ["<builtin>.len"]}